{
  "title": "Yacht, rafiot et liqueur d'algues",
  "id": "yacht-rafiot-et-liqueur-dalgues",
  "system": "CoC7",
  "coreVersion": "11.308",
  "compatibility": {
    "minimum": "11",
    "verified": "11.308"
  },
  "systemVersion": "0.10.5",
  "esmodules": [
    "scripts/autoscale.js",
    "scripts/better-entity-link.js",
    "scripts/highlight.js",
    "scripts/share-actor.js",
    "scripts/share-handout.js",
    "scripts/show-date.js"
  ],
  "styles": [
    "styles.css"
  ],
  "lastPlayed": "Sun Sep 17 2023 17:11:26 GMT+0200 (Central European Summer Time)",
  "playtime": 3302470,
  "safeMode": false
}